README.txt
setup.py
collective/__init__.py
collective.portlet.quote.egg-info/PKG-INFO
collective.portlet.quote.egg-info/SOURCES.txt
collective.portlet.quote.egg-info/dependency_links.txt
collective.portlet.quote.egg-info/entry_points.txt
collective.portlet.quote.egg-info/namespace_packages.txt
collective.portlet.quote.egg-info/not-zip-safe
collective.portlet.quote.egg-info/requires.txt
collective.portlet.quote.egg-info/top_level.txt
collective/portlet/__init__.py
collective/portlet/quote/__init__.py
collective/portlet/quote/config.py
collective/portlet/quote/configure.zcml
collective/portlet/quote/randomquote.pt
collective/portlet/quote/randomquote.py
collective/portlet/quote/version.txt
collective/portlet/quote/content/__init__.py
collective/portlet/quote/content/configure.zcml
collective/portlet/quote/content/quote.py
collective/portlet/quote/interfaces/__init__.py
collective/portlet/quote/interfaces/quote.py
collective/portlet/quote/locales/collective.portlet.quote.pot
collective/portlet/quote/locales/no/LC_MESSAGES/collective.portlet.quote.po
collective/portlet/quote/locales/sv/LC_MESSAGES/collective.portlet.quote.po
collective/portlet/quote/profiles/default/factorytool.xml
collective/portlet/quote/profiles/default/metadata.xml
collective/portlet/quote/profiles/default/portlets.xml
collective/portlet/quote/profiles/default/rolemap.xml
collective/portlet/quote/profiles/default/types.xml
collective/portlet/quote/profiles/default/types/Quote.xml
collective/portlet/quote/profiles/default/types/QuoteFolder.xml
collective/portlet/quote/tests/__init__.py
collective/portlet/quote/tests/base.py
collective/portlet/quote/tests/test_portlet.py
docs/HISTORY.txt
docs/INSTALL.txt
docs/LICENSE.GPL
docs/LICENSE.txt