Metadata-Version: 1.0
Name: collective.portlet.quote
Version: 1.0.1
Summary: A portlet showing random quotes from a folder
Home-page: http://jarn.com
Author: Jarn AS
Author-email: info@jarn.com
License: GPL
Keywords: random quote plone
Platform: UNKNOWN
Classifier: Framework :: Plone
Classifier: Programming Language :: Python
